<PAMDataset>
  <PAMRasterBand band="1">
    <Description>class_mask</Description>
    <Metadata>
      <MDI key="STATISTICS_MINIMUM">0</MDI>
      <MDI key="STATISTICS_MAXIMUM">255</MDI>
      <MDI key="STATISTICS_MEAN">0.034416255554017</MDI>
      <MDI key="STATISTICS_STDDEV">2.9622560131811</MDI>
      <MDI key="STATISTICS_VALID_PERCENT">70.56</MDI>
    </Metadata>
  </PAMRasterBand>
  <PAMRasterBand band="2">
    <Description>full_classification</Description>
    <Metadata>
      <MDI key="STATISTICS_MINIMUM">0</MDI>
      <MDI key="STATISTICS_MAXIMUM">7</MDI>
      <MDI key="STATISTICS_MEAN">1.2518033904806</MDI>
      <MDI key="STATISTICS_STDDEV">1.0557548831031</MDI>
      <MDI key="STATISTICS_VALID_PERCENT">70.56</MDI>
    </Metadata>
  </PAMRasterBand>
  <PAMRasterBand band="3">
    <Description>built_probability</Description>
    <Metadata>
      <MDI key="STATISTICS_MINIMUM">2</MDI>
      <MDI key="STATISTICS_MAXIMUM">77</MDI>
      <MDI key="STATISTICS_MEAN">5.2605406442125</MDI>
      <MDI key="STATISTICS_STDDEV">9.487316632671</MDI>
      <MDI key="STATISTICS_VALID_PERCENT">70.56</MDI>
    </Metadata>
  </PAMRasterBand>
  <PAMRasterBand band="4">
    <Description>bare_probability</Description>
  </PAMRasterBand>
</PAMDataset>
